[
  { "id": "817984ac8f9d0d75", "type": "tab", "label": "高德 - 天气查询", "disabled": false, "info": "", "env": [] },
  { "id": "f8c0d384d3dc8d05", "type": "group", "z": "817984ac8f9d0d75", "name": "天气查询", "style": { "label": true }, "nodes": ["45684c93962df726", "1678b4a6f9054b6a", "b21c276dca2c6de8", "94c8a14d758c62d7", "10626aa83cc36ae3"], "x": 214, "y": 119, "w": 672, "h": 162 },
  {
    "id": "45684c93962df726",
    "type": "inject",
    "z": "817984ac8f9d0d75",
    "g": "f8c0d384d3dc8d05",
    "name": "",
    "props": [{ "p": "payload" }, { "p": "topic", "vt": "str" }],
    "repeat": "",
    "crontab": "",
    "once": false,
    "onceDelay": 0.1,
    "topic": "",
    "payload": "",
    "payloadType": "date",
    "x": 310,
    "y": 240,
    "wires": [["1678b4a6f9054b6a"]]
  },
  {
    "id": "1678b4a6f9054b6a",
    "type": "amaps-weather",
    "z": "817984ac8f9d0d75",
    "g": "f8c0d384d3dc8d05",
    "name": "",
    "amaps": "ab0f695bc424abb4",
    "city": "110101",
    "city_type": "str",
    "extensions": "base",
    "extensions_type": "list",
    "x": 540,
    "y": 240,
    "wires": [["b21c276dca2c6de8"]]
  },
  {
    "id": "b21c276dca2c6de8",
    "type": "debug",
    "z": "817984ac8f9d0d75",
    "g": "f8c0d384d3dc8d05",
    "name": "debug 4",
    "active": true,
    "tosidebar": true,
    "console": false,
    "tostatus": false,
    "complete": "false",
    "statusVal": "",
    "statusType": "auto",
    "x": 780,
    "y": 200,
    "wires": []
  },
  {
    "id": "94c8a14d758c62d7",
    "type": "amaps-weather",
    "z": "817984ac8f9d0d75",
    "g": "f8c0d384d3dc8d05",
    "name": "",
    "amaps": "ab0f695bc424abb4",
    "city": "110101",
    "city_type": "str",
    "extensions": "all",
    "extensions_type": "list",
    "x": 540,
    "y": 160,
    "wires": [["b21c276dca2c6de8"]]
  },
  {
    "id": "10626aa83cc36ae3",
    "type": "inject",
    "z": "817984ac8f9d0d75",
    "g": "f8c0d384d3dc8d05",
    "name": "",
    "props": [{ "p": "payload" }, { "p": "topic", "vt": "str" }],
    "repeat": "",
    "crontab": "",
    "once": false,
    "onceDelay": 0.1,
    "topic": "",
    "payload": "",
    "payloadType": "date",
    "x": 310,
    "y": 160,
    "wires": [["94c8a14d758c62d7"]]
  },
  { "id": "ab0f695bc424abb4", "type": "amaps-configurator", "name": "高德配置" }
]
